ros2top/__init__.py
ros2top/gpu_monitor.py
ros2top/main.py
ros2top/node_monitor.py
ros2top/node_registry.py
ros2top/ros2_utils.py
ros2top/ui/__init__.py
ros2top/ui/components.py
ros2top/ui/layout.py
ros2top/ui/terminal_ui.py
ros2top-0.2.0.data/data/include/ros2top/ros2top.hpp
ros2top-0.2.0.data/data/share/ros2top/cmake/ros2topConfig.cmake
ros2top-0.2.0.dist-info/licenses/LICENSE
ros2top-0.2.0.dist-info/METADATA
ros2top-0.2.0.dist-info/WHEEL
ros2top-0.2.0.dist-info/entry_points.txt
ros2top-0.2.0.dist-info/top_level.txt
ros2top-0.2.0.dist-info/RECORD
