Metadata-Version: 2.4
Name: ros2top
Version: 0.2.0
Summary: A real-time process monitor with support for ROS2 nodes, showing CPU, RAM, and GPU usage
Author-email: Ahmed Radwan <ahmed.ali.radwan94@gmail.com>
License-Expression: MIT
Project-URL: Homepage, https://github.com/AhmedARadwan/ros2top
Project-URL: Bug Reports, https://github.com/AhmedARadwan/ros2top/issues
Project-URL: Source, https://github.com/AhmedARadwan/ros2top
Keywords: monitoring,process,ros2,gpu,cpu,memory,nodes,system
Classifier: Development Status :: 3 - Alpha
Classifier: Intended Audience :: Developers
Classifier: Intended Audience :: System Administrators
Classifier: Operating System :: OS Independent
Classifier: Programming Language :: Python :: 3
Classifier: Programming Language :: Python :: 3.8
Classifier: Programming Language :: Python :: 3.9
Classifier: Programming Language :: Python :: 3.10
Classifier: Programming Language :: Python :: 3.11
Classifier: Programming Language :: Python :: 3.12
Classifier: Topic :: System :: Monitoring
Classifier: Topic :: System :: Systems Administration
Classifier: Topic :: Software Development :: Libraries :: Python Modules
Requires-Python: >=3.8
License-File: LICENSE
Requires-Dist: psutil>=5.8.0
Requires-Dist: pynvml>=11.0.0
Dynamic: license-file
